wayfinder/__about__.py
wayfinder/__init__.py
wayfinder/assets.py
wayfinder/mesh_generator.py
wayfinder/utils.py
amon_wayfinder-0.0.8.dist-info/METADATA
amon_wayfinder-0.0.8.dist-info/WHEEL
amon_wayfinder-0.0.8.dist-info/licenses/LICENSE.txt
amon_wayfinder-0.0.8.dist-info/RECORD
